NetFT/__init__.py
NetFT-2.0.1.data/scripts/NetFT
NetFT-2.0.1.dist-info/LICENSE
NetFT-2.0.1.dist-info/METADATA
NetFT-2.0.1.dist-info/WHEEL
NetFT-2.0.1.dist-info/top_level.txt
NetFT-2.0.1.dist-info/RECORD
