Metadata-Version: 2.1
Name: NetFT
Version: 2.0.1
Summary: A Python library for reading data from ATI Force/Torque sensors with a Net F/T interface box.
Home-page: https://github.com/CameronDevine/NetFT
Author: Cameron Devine
Author-email: camdev@uw.edu
License: BSD
Project-URL: Documentation, https://netft.readthedocs.io/en/latest/
Keywords: Robotics Force Torque Sensor NetFT ATI Data Logging
Platform: UNKNOWN
